jinjaMarkdown/__init__.py
jinjaMarkdown/markdownExtension.py
test/__init__.py
test/markdownExtensionTest.py
jinjaMarkdown-0.0.7.dist-info/LICENSE
jinjaMarkdown-0.0.7.dist-info/METADATA
jinjaMarkdown-0.0.7.dist-info/WHEEL
jinjaMarkdown-0.0.7.dist-info/top_level.txt
jinjaMarkdown-0.0.7.dist-info/RECORD
