Metadata-Version: 2.1
Name: jinjaMarkdown
Version: 0.0.7
Summary: A package containing a markdown filter for jinja2
Home-page: https://github.com/AnthonyGithubCorner/jinjaMarkdown
Author: Anthony Lazar
Author-email: alazar@uwaterloo.ca
License: UNKNOWN
Platform: UNKNOWN
Classifier: Programming Language :: Python :: 3
Classifier: License :: OSI Approved :: MIT License
Classifier: Operating System :: OS Independent
Requires-Python: >=3.6
License-File: LICENSE
